[
  {
    "id": "10d51e3b-e967-4e3e-af3c-59936d3f6e1d",
    "document_id": "doc_45",
    "content": "Ayman Habib, Jennifer Hicks, Scott Delp, Ajay Seth, Joy Ku, Matt Petrucci, Carmichael Ong, Thomas Uchida, Nicholas Bianco, Diane Bush, Jacqueline Tran Forum Statistics and Usage SimTK is maintained through Grant R01GM124443 01A1 from the National Institutes of Health (NIH). It was initially developed as part of the Simbios project funded by the NIH as part of the NIH Roadmap for Medical Research, Grant U54 GM072970. Our Pledge and Your Responsibility Feedback About Join Version 4.2.2. Website design by Viewfarm . Icons created by SimTK team using art by GraphBerry from www.flaticon.com under a CC BY 3.0 license. Forked from FusionForge 6.0.5. #FDF8E1 @light_yellow #F75236 @red #F5B563 @orange #81A5D4 @light_blue #5E96E1 @dark_blue #505050 @dark_grey #000000 @black #A7A7A7 @light_grey Feedback",
    "metadata": {
      "source": "https://simtk.org/plugins/phpBB/indexPhpbb.php?group_id=91&pluginname=phpBB",
      "title": "SimTK: OpenSim: phpBB",
      "section": "OpenSim Share Follow Project Follow publicly Follow privately Unfollow See followers (313) List Map More info 91 About Project summary Project statistics Downloads Summary Project Activity Plots Geography of Use Forum Statistics Publications Team members Downloads Documents Forums Source Code Issues View trackers Bugs Bugs tracker Submit new Follow Features Features tracker Submit new Follow Suggested Ideas Suggested Ideas tracker Submit new Follow News About Project summary Project statistics Downloads Summary Project Activity Plots Geography of Use Forum Statistics Publications Team members Downloads Documents Forums Source Code Issues View trackers Bugs Bugs tracker Submit new Follow Features Features tracker Submit new Follow Suggested Ideas Suggested Ideas tracker Submit new Follow News Forum Moderators:",
      "hierarchy": [
        "plugins",
        "phpBB",
        "indexPhpbb.php"
      ],
      "content_type": "reference",
      "position": 0,
      "tags": [
        "reference",
        "general",
        "intermediate"
      ]
    }
  }
]